{
  "$schema": "https://developer.microsoft.com/json-schemas/fabric/item/report/definition/visualContainer/1.4.0/schema.json",
  "name": "1b4cc3dcd634796167dc",
  "position": {
    "x": 19.024390243902438,
    "y": 16.097560975609756,
    "z": 8000,
    "height": 58.536585365853661,
    "width": 427.3170731707317,
    "tabOrder": 8000
  },
  "visual": {
    "visualType": "textbox",
    "objects": {
      "general": [
        {
          "properties": {
            "paragraphs": [
              {
                "textRuns": [
                  {
                    "value": "New Medical dashboard",
                    "textStyle": {
                      "fontWeight": "bold",
                      "fontSize": "20pt",
                      "textDecoration": "underline"
                    }
                  }
                ]
              }
            ]
          }
        }
      ]
    },
    "drillFilterOtherVisuals": true
  }
}